{
  "project_info": {
    "project_number": "342236375709",
    "firebase_url": "https://mysukan-dev.firebaseio.com",
    "project_id": "mysukan-dev",
    "storage_bucket": "mysukan-dev.appspot.com"
  },
  "client": [
    {
      "client_info": {
        "mobilesdk_app_id": "1:342236375709:android:d2a47c2c6a07c728",
        "android_client_info": {
          "package_name": "tremblay412.com.mysukan"
        }
      },
      "oauth_client": [
        {
          "client_id": "342236375709-abpbd7hbpkmarrgtldjt1j39ppl8eg8k.apps.googleusercontent.com",
          "client_type": 3
        }
      ],
      "api_key": [
        {
          "current_key": "AIzaSyAqL-SuIFDEuN49NymFzs0h9I8myZdJmY4"
        }
      ],
      "services": {
        "analytics_service": {
          "status": 1
        },
        "appinvite_service": {
          "status": 1,
          "other_platform_oauth_client": []
        },
        "ads_service": {
          "status": 2
        }
      }
    }
  ],
  "configuration_version": "1"
}